sagify/Dockerfile
sagify/__init__.py
sagify/__main__.py
sagify/log.py
sagify/api/__init__.py
sagify/api/build.py
sagify/api/cloud.py
sagify/api/hyperparameter_tuning.py
sagify/api/initialize.py
sagify/api/llm.py
sagify/api/local.py
sagify/api/push.py
sagify/commands/__init__.py
sagify/commands/build.py
sagify/commands/cloud.py
sagify/commands/configure.py
sagify/commands/initialize.py
sagify/commands/llm.py
sagify/commands/local.py
sagify/commands/push.py
sagify/commands/custom_validators/__init__.py
sagify/commands/custom_validators/validators.py
sagify/config/__init__.py
sagify/config/config.py
sagify/llm_gateway/__init__.py
sagify/llm_gateway/main.py
sagify/llm_gateway/api/__init__.py
sagify/llm_gateway/api/v1/__init__.py
sagify/llm_gateway/api/v1/exceptions.py
sagify/llm_gateway/api/v1/routes.py
sagify/llm_gateway/api/v1/endpoints/__init__.py
sagify/llm_gateway/api/v1/endpoints/chat.py
sagify/llm_gateway/api/v1/endpoints/embeddings.py
sagify/llm_gateway/api/v1/endpoints/images.py
sagify/llm_gateway/core/__init__.py
sagify/llm_gateway/providers/__init__.py
sagify/llm_gateway/providers/client_factory.py
sagify/llm_gateway/providers/aws/__init__.py
sagify/llm_gateway/providers/aws/sagemaker.py
sagify/llm_gateway/providers/openai/__init__.py
sagify/llm_gateway/providers/openai/client.py
sagify/llm_gateway/schemas/__init__.py
sagify/llm_gateway/schemas/chat.py
sagify/llm_gateway/schemas/embeddings.py
sagify/llm_gateway/schemas/images.py
sagify/llm_gateway/services/__init__.py
sagify/llm_gateway/services/chat.py
sagify/llm_gateway/services/embeddings.py
sagify/llm_gateway/services/images.py
sagify/sagemaker/__init__.py
sagify/sagemaker/sagemaker.py
sagify/streaming_inference/__init__.py
sagify/streaming_inference/streaming_inference.py
sagify/template/sagify_base/Dockerfile
sagify/template/sagify_base/__init__.py
sagify/template/sagify_base/build.sh
sagify/template/sagify_base/executor.sh
sagify/template/sagify_base/push.sh
sagify-0.25.4.dist-info/LICENSE
sagify-0.25.4.dist-info/METADATA
sagify-0.25.4.dist-info/WHEEL
sagify-0.25.4.dist-info/entry_points.txt
sagify-0.25.4.dist-info/top_level.txt
sagify-0.25.4.dist-info/zip-safe
sagify-0.25.4.dist-info/RECORD
