Metadata-Version: 2.1
Name: sagify
Version: 0.25.4
Summary: Machine Learning Training, Tuning and Deployment on AWS
Home-page: https://github.com/Kenza-AI/sagify
Author: Pavlos Mitsoulis Ntompos, Ioakeim (Joakim) Lazakis, Dionysis Varelas
Author-email: p.mitsoulis@gmail.com, ilazakis@gmail.com, dionvarelas@gmail.com
License: MIT
Keywords: sagify llm multi-modal-model foundation-model llm-production machine-learning machine-learning-deploy machine-learning-production deep-learning-production deep-learning cli aws sagemaker tensorflow mxnet scikit-learn artificial-intelligence keras cntk deploy
Classifier: Development Status :: 5 - Production/Stable
Classifier: License :: OSI Approved :: MIT License
Classifier: Intended Audience :: Developers
Classifier: Intended Audience :: Science/Research
Classifier: Natural Language :: English
Classifier: Programming Language :: Python :: 3
Classifier: Programming Language :: Python :: 3.7
Classifier: Programming Language :: Python :: 3.8
Classifier: Programming Language :: Python :: 3.9
Classifier: Programming Language :: Python :: 3.10
Classifier: Programming Language :: Python :: 3.11
Classifier: Topic :: Scientific/Engineering
Classifier: Topic :: Scientific/Engineering :: Artificial Intelligence
Classifier: Environment :: Console
Requires-Python: ~=3.7
License-File: LICENSE
Requires-Dist: click <8.1.99,>=8.1.0
Requires-Dist: docker <7.0.99,>=7.0.0
Requires-Dist: future <0.18.99,>=0.18.0
Requires-Dist: sagemaker <2.207.99,>=2.207.0
Requires-Dist: six <1.16.99,>=1.16
